mininode/__init__.py
mininode/_requests.py
mininode/client.py
mininode/api/__init__.py
mininode/api/base.py
mininode/api/lightnode.py
mininode/crypto/__init__.py
mininode/crypto/account.py
mininode/crypto/sign_trx.py
mininode/proto/__init__.py
mininode/proto/quorum_pb2.py
mininode/utils/__init__.py
mininode/utils/image.py
mininode/utils/trx_retweet.py
mininode/utils/url.py
mininode-0.3.4.dist-info/LICENSE
mininode-0.3.4.dist-info/METADATA
mininode-0.3.4.dist-info/WHEEL
mininode-0.3.4.dist-info/top_level.txt
mininode-0.3.4.dist-info/RECORD
