Metadata-Version: 2.1
Name: mininode
Version: 0.3.4
Summary: a mini python sdk for quorum lightnode with http/https requests to quorum fullnode
Home-page: https://github.com/liujuanjuan1984/quorum-mininode-python
Author: liujuanjuan1984, zhangwm404
Author-email: qiaoanlu@163.com
Project-URL: Github Repo, https://github.com/liujuanjuan1984/quorum-mininode-python
Project-URL: Bug Tracker, https://github.com/liujuanjuan1984/quorum-mininode-python/issues
Project-URL: About Quorum, https://github.com/rumsystem/quorum
Keywords: rumsystem,quorum,lightnode,sdk
Classifier: Programming Language :: Python :: 3
Classifier: Programming Language :: Python :: 3.9
Classifier: License :: OSI Approved :: GNU General Public License v3 (GPLv3)
Classifier: Operating System :: OS Independent
Requires-Python: >=3.5
License-File: LICENSE
Requires-Dist: requests
Requires-Dist: filetype
Requires-Dist: pillow
Requires-Dist: pygifsicle
Requires-Dist: eth-keys
Requires-Dist: protobuf
Requires-Dist: eth-account
